elveirdor/__init__.py
elveirdor/cli.py
elveirdor/decode.py
elveirdor/export.py
elveirdor/grid.py
elveirdor/mosaic.py
elveirdor/pipeline.py
elveirdor/run_elveirdor.py
elveirdor/core/__init__.py
elveirdor/core/engine.py
elveirdor-2.1.3.dist-info/METADATA
elveirdor-2.1.3.dist-info/WHEEL
elveirdor-2.1.3.dist-info/entry_points.txt
elveirdor-2.1.3.dist-info/top_level.txt
elveirdor-2.1.3.dist-info/RECORD
