Metadata-Version: 2.4
Name: elveirdor
Version: 2.1.3
Summary: Elveirdor Infinity Computing Pipeline with visual generation, decoding, and export features.
Author: Elveirdor Systems
Requires-Python: >=3.8
Requires-Dist: numpy
Requires-Dist: pillow
Requires-Dist: matplotlib
Dynamic: author
Dynamic: requires-dist
Dynamic: requires-python
Dynamic: summary
